README.md
setup.py
lineseg/__init__.py
lineseg/correct.py
lineseg/dataset.py
lineseg/model.py
lineseg/seg.py
lineseg/training.py
lineseg/util.py
lineseg.egg-info/PKG-INFO
lineseg.egg-info/SOURCES.txt
lineseg.egg-info/dependency_links.txt
lineseg.egg-info/requires.txt
lineseg.egg-info/top_level.txt