Metadata-Version: 2.1
Name: lineseg
Version: 0.1
Summary: Line-Level Segmentation using an ARU-Net architecture
Home-page: https://github.com/BYU-Handwriting-Lab/LineSegmentation
Author: BYU-Handwriting-Lab
Keywords: BYU segmentation line handwriting recognition
